Metadata-Version: 2.1
Name: sphinx-multiversion-pre-post-build
Version: 0.2.4
Summary: Add support for multiple versions to sphinx
Home-page: https://github.com/Cedric-Magnan/sphinx-multiversion
Author: Cedric Magnan
Author-email: cedric.magnan@artefact.com
License: BSD
Platform: UNKNOWN
Classifier: License :: OSI Approved :: BSD License
Classifier: Programming Language :: Python :: 3
Classifier: Programming Language :: Python :: 3.6
Classifier: Programming Language :: Python :: 3.7
Classifier: Programming Language :: Python :: 3.8
Classifier: Programming Language :: Python :: 3.9
Requires-Dist: sphinx (>=2.1)
